{
  "bitsAndPieces": [
    { "str": "A",   "clue": "Ace", "alt": "AI (for A-1)" },
    { "str": "A",   "clue": "Alfa", "eg": "ICAO phonetic alphabet" },
    { "str": "B",   "clue": "Bravo", "eg": "ICAO phonetic alphabet" },
    { "str": "C",   "clue": "About", "eg": "circa", "alt": "CA; RE" },
    { "str": "C",   "clue": "Charlie", "eg": "ICAO phonetic alphabet" },
    { "str": "CA",  "clue": "About", "eg": "circa", "alt": "C; RE" },
    { "str": "D",   "clue": "Delta", "eg": "ICAO phonetic alphabet" },
    { "str": "D",   "clue": "Land's End", "eg": "Place name" },
    { "str": "E",   "clue": "Echo", "eg": "ICAO phonetic alphabet" },
    { "str": "F",   "clue": "Foxtrot", "eg": "ICAO phonetic alphabet" },
    { "str": "G",   "clue": "Golf", "eg": "ICAO phonetic alphabet" },
    { "str": "H",   "clue": "Hotel", "eg": "ICAO phonetic alphabet" },
    { "str": "I",   "clue": "India", "eg": "ICAO phonetic alphabet" },
    { "str": "IO",  "clue": "Lionheart" },
    { "str": "J",   "clue": "Juliett", "eg": "ICAO phonetic alphabet" },
    { "str": "K",   "clue": "Kilo", "eg": "ICAO phonetic alphabet" },
    { "str": "L",   "clue": "Lima", "eg": "ICAO phonetic alphabet" },
    { "str": "L",   "clue": "Left" },
    { "str": "M",   "clue": "Mike", "eg": "ICAO phonetic alphabet" },
    { "str": "M",   "clue": "Maidenhead", "eg": "Place name" },
    { "str": "N",   "clue": "November", "eg": "ICAO phonetic alphabet" },
    { "str": "O",   "clue": "Oscar", "eg": "ICAO phonetic alphabet" },
    { "str": "O",   "clue": "Heart of stone" },
    { "str": "P",   "clue": "Papa", "eg": "ICAO phonetic alphabet" },
    { "str": "Q",   "clue": "Quebec", "eg": "ICAO phonetic alphabet" },
    { "str": "R",   "clue": "Romeo", "eg": "ICAO phonetic alphabet" },
    { "str": "R",   "clue": "Right" },
    { "str": "RE",  "clue": "About", "alt": "C, CA" },
    { "str": "S",   "clue": "Sierra", "eg": "ICAO phonetic alphabet" },
    { "str": "S",   "clue": "Head of state" },
    { "str": "T",   "clue": "Tango", "eg": "ICAO phonetic alphabet" },
    { "str": "TA",  "clue": "Thanks" },
    { "str": "U",   "clue": "Uniform", "eg": "ICAO phonetic alphabet" },
    { "str": "V",   "clue": "Victor", "eg": "ICAO phonetic alphabet" },
    { "str": "W",   "clue": "Whiskey", "eg": "ICAO phonetic alphabet" },
    { "str": "X",   "clue": "X-Ray", "eg": "ICAO phonetic alphabet" },
    { "str": "Y",   "clue": "Yankee", "eg": "ICAO phonetic alphabet" },
    { "str": "Z",   "clue": "Zulu", "eg": "ICAO phonetic alphabet" },
    { "str": "A",   "clue": "One", "alt": "I" },
    { "str": "UN",  "clue": "A French...", "eg": "Translation", "alt": "UNE" },
    { "str": "UNE", "clue": "A French...", "eg": "Translation", "alt": "UN" },
    { "str": "LE",  "clue": "The French...", "eg": "Translation", "alt": "LA; LES" },
    { "str": "LA",  "clue": "The French...", "eg": "Translation", "alt": "LE; LES" },
    { "str": "LES", "clue": "The French...", "eg": "Translation", "alt": "LE; LA" },
    { "str": "A",   "clue": "Note; Key", "eg": "Music", "alt": "B; C; D; E; F; G" },
    { "str": "B",   "clue": "Note; Key", "eg": "Music", "alt": "A; C; D; E; F; G" },
    { "str": "C",   "clue": "Note; Key", "eg": "Music", "alt": "A; B, D, E, F; G" },
    { "str": "D",   "clue": "Note; Key", "eg": "Music", "alt": "A; B; C; E; F; G" },
    { "str": "E",   "clue": "Note; Key", "eg": "Music", "alt": "A; B; C; D; F; G" },
    { "str": "F",   "clue": "Note; Key", "eg": "Music", "alt": "A; B; C; D; E; G" },
    { "str": "G",   "clue": "Note; Key", "eg": "Music", "alt": "A; B; C; D; E; F" },
    { "str": "R",   "clue": "Never-ending" },
    { "str": "K",   "clue": "Kick-start" },
    { "str": "NY",  "clue": "New York" },
    { "str": "I",   "clue": "One", "alt": "A; Answer to 1 across/down" },
    { "str": "II",  "clue": "Two; 2", "alt": "Answer to 2 across/down" },
    { "str": "IV",  "clue": "Four; 4", "alt": "Answer to 4 across/down" },
    { "str": "V",   "clue": "Five; 5", "alt": "Answer to 5 across/down" },
    { "str": "VI",  "clue": "Six; 6", "alt": "Answer to 6 across/down" },
    { "str": "IX",  "clue": "Nine; 9", "alt": "Answer to 9 across/down" },
    { "str": "X",   "clue": "Ten; 10", "alt": "Answer to 10 across/down" },
    { "str": "L",   "clue": "Fifty; 50", "eg": "Roman numerals" },
    { "str": "C",   "clue": "Hundred; 100" },
    { "str": "M",   "clue": "Thousand; 1000" },
    { "str": "D",   "clue": "Five hundred; 500", "eg": "Roman numerals" },
    { "str": "B",   "clue": "Boy" },
    { "str": "G",   "clue": "Girl" },
    { "str": "B",   "clue": "Bold", "eg": "Typography" },
    { "str": "B",   "clue": "Born", "eg": "Family tree", "alt": "NEE" },
    { "str": "D",   "clue": "Died", "eg": "Family tree" },
    { "str": "M",   "clue": "Married", "eg": "Family tree" },
    { "str": "B",   "clue": "Bowled", "eg": "Cricket", "alt": "" },
    { "str": "B",   "clue": "Belgium" },
    { "str": "K",   "clue": "King", "eg": "Chess" },
    { "str": "Q",   "clue": "Queen", "eg": "Chess" },
    { "str": "R",   "clue": "Rook", "eg": "Chess" },
    { "str": "B",   "clue": "Bishop", "eg": "Chess" },
    { "str": "N",   "clue": "Knight", "eg": "Chess" },
    { "str": "P",   "clue": "Pawn", "eg": "Chess" },
    { "str": "C",   "clue": "Century" },
    { "str": "C",   "clue": "Caught", "eg": "Cricket" },
    { "str": "H",   "clue": "Hot", "eg": "Water tap" },
    { "str": "C",   "clue": "Cold", "eg": "Water tap" },
    { "str": "C",   "clue": "See", "eg": "Soundalike" },
    { "str": "U",   "clue": "You", "eg": "Soundalike" },
    { "str": "ON",  "clue": "Aboard", "eg": "Synonym", "alt": "SS" },
    { "str": "SS",  "clue": "Aboard", "eg": "Ship", "alt": "ON" },
    { "str": "G",   "clue": "Acceleration", "eg": "Physics" },
    { "str": "HAM", "clue": "Actor" },
    { "str": "A",   "clue": "Adult" },
    { "str": "AM",  "clue": "Morning" },
    { "str": "PM",  "clue": "Afternoon" },
    { "str": "CIA", "clue": "Agency" },
    { "str": "V",   "clue": "Against; Versus", "alt": "VS" },
    { "str": "VS",  "clue": "Against; Versus", "alt": "V" },
    { "str": "BA",  "clue": "Airline", "eg": "British Airways" },
    { "str": "OR",  "clue": "Alternatively" },
    { "str": "UR",  "clue": "Ancient city" },
    { "str": "P",   "clue": "Apple core" },
    { "str": "IN",  "clue": "At home" },
    { "str": "B",   "clue": "Birkenhead" },
    { "str": "L",   "clue": "Beginner", "eg": "Learner driver" },
    { "str": "B",   "clue": "Bottle opener" },
    { "str": "X",   "clue": "By", "eg": "Giving dimensions" },
    { "str": "O",   "clue": "Circle; Ring" },
    { "str": "CE",  "clue": "Church", "eg": "of England", "alt": "CH; RC" },
    { "str": "CH",  "clue": "Church", "alt": "CE; RC" },
    { "str": "RC",  "clue": "Church", "eg": "Roman Catholic", "alt": "CE; CH" },
    { "str": "IT",  "clue": "City centre" },
    { "str": "I",   "clue": "Current", "eg": "Physics symbol", "alt": "AC; DC" },
    { "str": "AC",  "clue": "Current", "eg": "Alternating current", "alt": "I; DC" },
    { "str": "DC",  "clue": "Current", "eg": "Direct current", "alt": "I ; AC" },
    { "str": "H",   "clue": "Hearts", "eg": "Playing cards" },
    { "str": "C",   "clue": "Clubs", "eg": "Playing cards" },
    { "str": "S",   "clue": "Spades", "eg": "Playing cards" },
    { "str": "D",   "clue": "Diamonds", "eg": "Playing cards", "alt": "ICE" },
    { "str": "ICE", "clue": "Diamonds", "alt": "D" },
    { "str": "",   "clue": "", "eg": "", "alt": "" },
    { "str": "",   "clue": "", "eg": "", "alt": "" },
    { "str": "",   "clue": "", "eg": "", "alt": "" }
  ]
}
